<?xml version="1.0" encoding="UTF-8"?>
<!DOCTYPE mapper PUBLIC "-//mybatis.org//DTD Mapper 3.0//EN" 
"http://mybatis.org/dtd/mybatis-3-mapper.dtd">

<mapper namespace="com.ez.ezBears.attendance.model.AttendanceDAO">
	<select id="selectByMemNo" parameterType="int" resultType="attendanceVo">
		select * from attendance where MEM_NO = #{memNo}
	</select>
 
 	<insert id="insertAttendance" parameterType="int">
 		insert into attendance(attendance_no, mem_no, in_time, status)
 		values(attendance_seq.nextval, #{memNo}, sysdate, '출근 중')
 	</insert>
	
	<update id="goHome" parameterType="int">
		update attendance 
		set out_time = sysdate
		where attendance_no = #{attendanceNo}
	</update>
	
	<select id="selectAttendanceNo" parameterType="attendanceVo" resultType="int">
		select attendance_no from attendance where mem_no = #{memNo} and rownum = 1 order by attendance_no desc
	</select>
	
	<select id="selectRecentAttendance" parameterType="int" resultType="attendanceVo">
		select * from attendance where mem_no = #{memNo} and rownum = 1 order by attendance_no desc
	</select>
 
 
 
 
</mapper>